MANIFEST.in
README.txt
setup.py
collective/__init__.py
collective.mrwiggin.egg-info/PKG-INFO
collective.mrwiggin.egg-info/SOURCES.txt
collective.mrwiggin.egg-info/dependency_links.txt
collective.mrwiggin.egg-info/entry_points.txt
collective.mrwiggin.egg-info/namespace_packages.txt
collective.mrwiggin.egg-info/not-zip-safe
collective.mrwiggin.egg-info/requires.txt
collective.mrwiggin.egg-info/top_level.txt
collective/mrwiggin/__init__.py
collective/mrwiggin/configure.zcml
collective/mrwiggin/editmanager.pt
collective/mrwiggin/editmanager.py
collective/mrwiggin/editmanager_macros.pt
collective/mrwiggin/interfaces.py
collective/mrwiggin/kss.py
collective/mrwiggin/main_layout.pt
collective/mrwiggin/main_layout.py
collective/mrwiggin/manage_portlets.pt
collective/mrwiggin/tests.py
collective/mrwiggin/traversable.py
collective/mrwiggin/profiles/default/browserlayer.xml
collective/mrwiggin/profiles/default/metadata.xml
collective/mrwiggin/profiles/default/registry.xml
collective/mrwiggin/static/close.png
collective/mrwiggin/static/manage_layout.css
collective/mrwiggin/static/manage_layout.js