Metadata-Version: 1.0
Name: collective.mrwiggin
Version: 0.1a1
Summary: Forget about viewlets, it's portlets time! Ah, yes - it's Mr Wiggin of Ironside and Malone.
Home-page: http://github.com/garbas/collective.mrwiggin
Author: Rok Garbas
Author-email: rok2garbas.si
License: GPL
Keywords: plone portlets
Platform: UNKNOWN
Classifier: Framework :: Plone
Classifier: Programming Language :: Python
